gradient_free_objective_functions/__init__.py
gradient_free_objective_functions/convex.py
gradient_free_objective_functions/non_convex.py
gradient_free_objective_functions/visualize.py
gradient_free_objective_functions-0.0.1.dist-info/LICENSE
gradient_free_objective_functions-0.0.1.dist-info/METADATA
gradient_free_objective_functions-0.0.1.dist-info/WHEEL
gradient_free_objective_functions-0.0.1.dist-info/top_level.txt
gradient_free_objective_functions-0.0.1.dist-info/RECORD
